basic_options/__init__.py
basic_options/basic_options.py
basic_options-0.2.0.dist-info/LICENSE
basic_options-0.2.0.dist-info/METADATA
basic_options-0.2.0.dist-info/WHEEL
basic_options-0.2.0.dist-info/top_level.txt
basic_options-0.2.0.dist-info/RECORD
