Metadata-Version: 2.1
Name: basic-options
Version: 0.2.0
Summary: This package provides a basic way to create configuration files, especially for tkinter GUI applictions.
Author: DuncanRuns
License: MIT License        
Project-URL: Homepage, https://github.com/DuncanRuns/basic_options
Project-URL: Bug Tracker, https://github.com/DuncanRuns/basic_options/issues
Classifier: Programming Language :: Python :: 3
Classifier: License :: OSI Approved :: MIT License
Classifier: Operating System :: OS Independent
Requires-Python: >=3.7
License-File: LICENSE
